linq_py_net/__init__.py
linq_py_net/list_linq.py
linq_py_net-0.0.3.dist-info/METADATA
linq_py_net-0.0.3.dist-info/WHEEL
linq_py_net-0.0.3.dist-info/top_level.txt
linq_py_net-0.0.3.dist-info/RECORD
