Metadata-Version: 2.1
Name: linq_py_net
Version: 0.0.3
Summary: Extensions methods for the list, inspired in linq csharp
Author: Wellington Junior
Keywords: python,linq,csharp,c#
Requires-Python: >=3.5
